streamlit_plotly_events_custom_data/__init__.py
streamlit_plotly_events_custom_data/frontend/build/asset-manifest.json
streamlit_plotly_events_custom_data/frontend/build/index.html
streamlit_plotly_events_custom_data/frontend/build/precache-manifest.eff04cf3a136aadf0d6bbcba4841ccfd.js
streamlit_plotly_events_custom_data/frontend/build/service-worker.js
streamlit_plotly_events_custom_data/frontend/build/static/js/2.f9b6a8a0.chunk.js
streamlit_plotly_events_custom_data/frontend/build/static/js/2.f9b6a8a0.chunk.js.LICENSE.txt
streamlit_plotly_events_custom_data/frontend/build/static/js/2.f9b6a8a0.chunk.js.map
streamlit_plotly_events_custom_data/frontend/build/static/js/main.2f5c6e5d.chunk.js
streamlit_plotly_events_custom_data/frontend/build/static/js/main.2f5c6e5d.chunk.js.map
streamlit_plotly_events_custom_data/frontend/build/static/js/runtime-main.44d30fc2.js
streamlit_plotly_events_custom_data/frontend/build/static/js/runtime-main.44d30fc2.js.map
streamlit_plotly_events_custom_data-0.0.6.3.dist-info/LICENSE
streamlit_plotly_events_custom_data-0.0.6.3.dist-info/METADATA
streamlit_plotly_events_custom_data-0.0.6.3.dist-info/WHEEL
streamlit_plotly_events_custom_data-0.0.6.3.dist-info/top_level.txt
streamlit_plotly_events_custom_data-0.0.6.3.dist-info/RECORD
